daspy/__init__.py
daspy/advanced_tools/__init__.py
daspy/advanced_tools/channel.py
daspy/advanced_tools/decomposition.py
daspy/advanced_tools/denoising.py
daspy/advanced_tools/fdct.py
daspy/advanced_tools/strain2vel.py
daspy/basic_tools/__init__.py
daspy/basic_tools/filter.py
daspy/basic_tools/freqattributes.py
daspy/basic_tools/preprocessing.py
daspy/basic_tools/visualization.py
daspy/core/__init__.py
daspy/core/collection.py
daspy/core/dasdatetime.py
daspy/core/example.pkl
daspy/core/make_example.py
daspy/core/read.py
daspy/core/section.py
daspy/core/util.py
daspy/core/write.py
daspy_toolbox-1.2.3.dist-info/licenses/LICENSE
daspy_toolbox-1.2.3.dist-info/METADATA
daspy_toolbox-1.2.3.dist-info/WHEEL
daspy_toolbox-1.2.3.dist-info/entry_points.txt
daspy_toolbox-1.2.3.dist-info/top_level.txt
daspy_toolbox-1.2.3.dist-info/RECORD
