Metadata-Version: 2.4
Name: DASPy-toolbox
Version: 1.2.3
Summary: DASPy is an open-source project dedicated to provide a python package for DAS (Distributed Acoustic Sensing) data processing, which comprises classic seismic data processing techniques and Specialized algorithms for DAS applications.
Home-page: https://github.com/HMZ-03/DASPy
Author: Minzhe Hu, Zefeng Li
Author-email: hmz2018@mail.ustc.edu.cn
Maintainer: Minzhe Hu
Maintainer-email: hmz2018@mail.ustc.edu.cn
License: MIT License
Classifier: Operating System :: OS Independent
Classifier: License :: OSI Approved :: MIT License
Classifier: Programming Language :: Python :: 3
Requires-Python: >=3.9
License-File: LICENSE
Requires-Dist: numpy
Requires-Dist: scipy>=1.13
Requires-Dist: matplotlib
Requires-Dist: geographiclib
Requires-Dist: pyproj
Requires-Dist: h5py
Requires-Dist: segyio
Requires-Dist: nptdms
Requires-Dist: tqdm
Dynamic: author
Dynamic: author-email
Dynamic: classifier
Dynamic: description
Dynamic: home-page
Dynamic: license
Dynamic: license-file
Dynamic: maintainer
Dynamic: maintainer-email
Dynamic: requires-dist
Dynamic: requires-python
Dynamic: summary
